{
    "menu": "Menu",
    "lngBtn": "English",
    "offers": "offers",
    "languageButton": "العربية",
    "bread": "bread",
    "comboOptions": "combo options",
    "drinks": "drinks",
    "extras": "extras",
    "size": "size",
    "addToCart": "add to cart",
    "Create an account": "Create an account",
    "Login": "Login",
    "Cart": "Cart",
    "Username": "Username",
    "Phone number": "Phone number",
    "Email": "Email",
    "Password": "Password",
    "Language": "Language",
    "My Loyalty Points": "My Loyalty Points",
    "Order history": "Order History",
    "Saved addresses": "Saved addresses",
    "My account": "My account",
    "Feedback": "Feedback",
    "Call Support": "Call Support",
    "Hello": "Hello"
}